neuroevobench/__init__.py
neuroevobench/_version.py
neuroevobench/eval.py
neuroevobench/run.py
neuroevobench/search.py
neuroevobench/hyperparams/__init__.py
neuroevobench/hyperparams/hyper.py
neuroevobench/hyperparams/default/ARS.yaml
neuroevobench/hyperparams/default/GESMR_GA.yaml
neuroevobench/hyperparams/default/LES.yaml
neuroevobench/hyperparams/default/LGA.yaml
neuroevobench/hyperparams/default/OpenES.yaml
neuroevobench/hyperparams/default/PGPE.yaml
neuroevobench/hyperparams/default/SAMR_GA.yaml
neuroevobench/hyperparams/default/SNES.yaml
neuroevobench/hyperparams/default/Sep_CMA_ES.yaml
neuroevobench/hyperparams/default/SimpleGA.yaml
neuroevobench/hyperparams/search_spaces/ARS.yaml
neuroevobench/hyperparams/search_spaces/GESMR_GA.yaml
neuroevobench/hyperparams/search_spaces/LES.yaml
neuroevobench/hyperparams/search_spaces/LGA.yaml
neuroevobench/hyperparams/search_spaces/OpenES.yaml
neuroevobench/hyperparams/search_spaces/PGPE.yaml
neuroevobench/hyperparams/search_spaces/SAMR_GA.yaml
neuroevobench/hyperparams/search_spaces/SNES.yaml
neuroevobench/hyperparams/search_spaces/Sep_CMA_ES.yaml
neuroevobench/hyperparams/search_spaces/SimpleGA.yaml
neuroevobench/metrics/__init__.py
neuroevobench/metrics/rliab.py
neuroevobench/postprocess/__init__.py
neuroevobench/postprocess/filter.py
neuroevobench/postprocess/plot.py
neuroevobench/problems/__init__.py
neuroevobench/problems/neb_evaluator.py
neuroevobench/problems/addition/__init__.py
neuroevobench/problems/addition/evaluator.py
neuroevobench/problems/addition/policy.py
neuroevobench/problems/addition/task.py
neuroevobench/problems/addition/wrapped.py
neuroevobench/problems/atari/__init__.py
neuroevobench/problems/atari/evaluator.py
neuroevobench/problems/atari/policy.py
neuroevobench/problems/atari/task.py
neuroevobench/problems/atari/wrapped.py
neuroevobench/problems/bbob/__init__.py
neuroevobench/problems/bbob/evaluator.py
neuroevobench/problems/bbob/wrapped.py
neuroevobench/problems/brax/__init__.py
neuroevobench-0.0.1.dist-info/LICENSE
neuroevobench-0.0.1.dist-info/METADATA
neuroevobench-0.0.1.dist-info/WHEEL
neuroevobench-0.0.1.dist-info/entry_points.txt
neuroevobench-0.0.1.dist-info/top_level.txt
neuroevobench-0.0.1.dist-info/RECORD
