Metadata-Version: 2.1
Name: neuroevobench
Version: 0.0.1
Summary: Neuroevolution Benchmark
Home-page: https://github.com/RobertTLange/neuroevobench
Download-URL: https://github.com/RobertTLange/neuroevobench/archive/v0.0.1.tar.gz
Author: Robert Tjarko Lange
Author-email: robertlange0@gmail.com
Platform: any
Classifier: Programming Language :: Python :: 3.7
Classifier: Programming Language :: Python :: 3.8
Classifier: Programming Language :: Python :: 3.9
Classifier: License :: OSI Approved :: MIT License
Classifier: Operating System :: OS Independent
Classifier: Topic :: Scientific/Engineering :: Artificial Intelligence
Requires-Python: >=3.7
License-File: LICENSE
Requires-Dist: flax
Requires-Dist: evosax
Requires-Dist: evojax
Requires-Dist: gymnax
Requires-Dist: tensorflow
Requires-Dist: tensorflow-datasets
Requires-Dist: mle-toolbox[full]
Requires-Dist: xgboost
Requires-Dist: wandb
Requires-Dist: brax
Requires-Dist: envpool
Requires-Dist: torch (==1.13.1)
Requires-Dist: torchvision (==0.14.1)
